
[
  {
    "name": "Buyurtma qilish",
    "path": "/",
    "icon": "FaCalendarAlt"
  },
  {
    "name": "Mening buyurtmalarim",
    "path": "/buyurtmalarim",
    "icon": "FaCalendarCheck"
  },
  {
    "name": "Soch va Soqol Stillari",
    "path": "/stillar",
    "icon": "FaCut"
  },
  {
    "name": "Sartarosh haqida",
    "path": "/sartarosh",
    "icon": "FaUserTie"
  },
  {
    "name": "AI bot",
    "path": "/ai-chat",
    "icon": "FaRobot"
  },
  {
    "name": "Sadoqat kartasi",
    "path": "/loyalty",
    "icon": "FaGift"
  }
]